fairness_indicators/__init__.py
fairness_indicators/example_model.py
fairness_indicators/example_model_test.py
fairness_indicators/fairness_indicators_metrics.py
fairness_indicators/version.py
fairness_indicators/remediation/__init__.py
fairness_indicators/remediation/weight_utils.py
fairness_indicators/remediation/weight_utils_test.py
fairness_indicators/tutorial_utils/__init__.py
fairness_indicators/tutorial_utils/util.py
fairness_indicators/tutorial_utils/util_test.py
fairness_indicators-0.48.0.dist-info/licenses/LICENSE
g3doc/__init__.py
fairness_indicators-0.48.0.dist-info/METADATA
fairness_indicators-0.48.0.dist-info/WHEEL
fairness_indicators-0.48.0.dist-info/top_level.txt
fairness_indicators-0.48.0.dist-info/RECORD
