Metadata-Version: 2.4
Name: fairness_indicators
Version: 0.48.0
Summary: Fairness Indicators
Home-page: https://github.com/tensorflow/fairness-indicators
Author: Google LLC
Author-email: packages@tensorflow.org
License: Apache 2.0
Keywords: tensorflow model analysis fairness indicators tensorboard machine learning
Classifier: Development Status :: 4 - Beta
Classifier: Intended Audience :: Developers
Classifier: Intended Audience :: Education
Classifier: Intended Audience :: Science/Research
Classifier: License :: OSI Approved :: Apache Software License
Classifier: Operating System :: OS Independent
Classifier: Programming Language :: Python :: 3
Classifier: Programming Language :: Python :: 3.9
Classifier: Programming Language :: Python :: 3 :: Only
Classifier: Topic :: Scientific/Engineering
Classifier: Topic :: Scientific/Engineering :: Mathematics
Classifier: Topic :: Scientific/Engineering :: Artificial Intelligence
Classifier: Topic :: Software Development
Classifier: Topic :: Software Development :: Libraries
Classifier: Topic :: Software Development :: Libraries :: Python Modules
Requires-Python: >=3.9,<4
License-File: LICENSE
Requires-Dist: tensorflow<2.18,>=2.17
Requires-Dist: tensorflow-hub<1.0.0,>=0.16.1
Requires-Dist: tensorflow-data-validation<2.0.0,>=1.17.0
Requires-Dist: tensorflow-model-analysis<0.49.0,>=0.48.0
Requires-Dist: witwidget<2,>=1.4.4
Requires-Dist: protobuf<6.0.0,>=4.21.6
Dynamic: author
Dynamic: author-email
Dynamic: classifier
Dynamic: description
Dynamic: description-content-type
Dynamic: home-page
Dynamic: keywords
Dynamic: license
Dynamic: license-file
Dynamic: requires-dist
Dynamic: requires-python
Dynamic: summary
